{"id":"node_modules/aws-sdk/apis/workmail-2017-10-01.paginators.json","dependencies":[{"name":"/home/yonatan/Programming/Node/wepApps/cat-blag/node_modules/aws-sdk/package.json","includedInParent":true,"mtime":1536129633814},{"name":"/home/yonatan/Programming/Node/wepApps/cat-blag/package.json","includedInParent":true,"mtime":1537792796422}],"generated":{"js":"module.exports = {\n  \"pagination\": {\n    \"ListAliases\": {\n      \"input_token\": \"NextToken\",\n      \"output_token\": \"NextToken\",\n      \"limit_key\": \"MaxResults\"\n    },\n    \"ListGroupMembers\": {\n      \"input_token\": \"NextToken\",\n      \"output_token\": \"NextToken\",\n      \"limit_key\": \"MaxResults\"\n    },\n    \"ListGroups\": {\n      \"input_token\": \"NextToken\",\n      \"output_token\": \"NextToken\",\n      \"limit_key\": \"MaxResults\"\n    },\n    \"ListMailboxPermissions\": {\n      \"input_token\": \"NextToken\",\n      \"output_token\": \"NextToken\",\n      \"limit_key\": \"MaxResults\"\n    },\n    \"ListOrganizations\": {\n      \"input_token\": \"NextToken\",\n      \"output_token\": \"NextToken\",\n      \"limit_key\": \"MaxResults\"\n    },\n    \"ListResources\": {\n      \"input_token\": \"NextToken\",\n      \"output_token\": \"NextToken\",\n      \"limit_key\": \"MaxResults\"\n    },\n    \"ListUsers\": {\n      \"input_token\": \"NextToken\",\n      \"output_token\": \"NextToken\",\n      \"limit_key\": \"MaxResults\"\n    }\n  }\n};"},"hash":"2ade62c611aaf301f08df83b2b4cb0b2","cacheData":{"env":{}}}